aws_chain_secrets/__init__.py
aws_chain_secrets/caster.py
aws_chain_secrets/client.py
aws_chain_secrets/exceptions.py
aws_chain_secrets/py.typed
aws_chain_secrets/secrets_manager.py
tests/__init__.py
tests/test_caster.py
aws_chain_secrets-1.0.3.dist-info/LICENSE
aws_chain_secrets-1.0.3.dist-info/METADATA
aws_chain_secrets-1.0.3.dist-info/WHEEL
aws_chain_secrets-1.0.3.dist-info/top_level.txt
aws_chain_secrets-1.0.3.dist-info/RECORD
