Metadata-Version: 2.1
Name: aws_chain_secrets
Version: 1.0.3
Summary: This aims to enable the use of one or more secrets from AWS SecretsManager.
Home-page: https://github.com/h5kure/aws_chain_secrets
Author: Hyouk Oh
Author-email: h.5.kure@gmail.com
Classifier: Programming Language :: Python :: 3.7
Classifier: Programming Language :: Python :: 3.8
Classifier: Programming Language :: Python :: 3.9
Classifier: Programming Language :: Python :: 3.10
Classifier: Programming Language :: Python :: 3.11
Classifier: License :: OSI Approved :: MIT License
Classifier: Operating System :: OS Independent
Requires-Python: >=3.7
License-File: LICENSE
Requires-Dist: boto3
